processor/__init__.py
processor/pipeline.hy
processor/storage.hy
processor/version.hy
processor/outputs/__init__.py
processor/outputs/debug.hy
processor/outputs/email.hy
processor/outputs/fanout.hy
processor/outputs/rss.hy
processor/outputs/slack.hy
processor/outputs/xmpp.hy
processor/sources/#web.hy#
processor/sources/__init__.py
processor/sources/github.hy
processor/sources/imap.hy
processor/sources/mix.hy
processor/sources/twitter.hy
processor/sources/web.hy
processor/utils/__init__.py
processor/utils/datastructures.hy
processor/utils/macro.hy
processor/utils/twitter.py
processor-0.7.0.dist-info/DESCRIPTION.rst
processor-0.7.0.dist-info/entry_points.txt
processor-0.7.0.dist-info/METADATA
processor-0.7.0.dist-info/metadata.json
processor-0.7.0.dist-info/RECORD
processor-0.7.0.dist-info/top_level.txt
processor-0.7.0.dist-info/WHEEL
