Metadata-Version: 2.0
Name: processor
Version: 0.7.0
Summary: A microframework to build source -> filter -> action workflows.
Home-page: https://github.com/svetlyak40wt/python-processor
Author: Alexander Artemenko
Author-email: svetlyak.40wt@gmail.com
License: BSD
Keywords: processing,devops,imap,rss,twitter
Platform: UNKNOWN
Classifier: Development Status :: 3 - Alpha
Classifier: Intended Audience :: Developers
Classifier: License :: OSI Approved :: BSD License
Classifier: Operating System :: Unix
Classifier: Operating System :: POSIX
Classifier: Programming Language :: Python
Classifier: Programming Language :: Python :: 3
Classifier: Programming Language :: Python :: 3.3
Classifier: Programming Language :: Python :: 3.4
Classifier: Programming Language :: Python :: Implementation :: CPython
Classifier: Programming Language :: Python :: Implementation :: PyPy
Classifier: Topic :: Utilities
Requires-Dist: hy
Requires-Dist: twiggy-goodies
Provides-Extra: outputs.slack
Requires-Dist: requests; extra == 'outputs.slack'
Provides-Extra: sources.twitter
Requires-Dist: requests-oauthlib; extra == 'sources.twitter'
Provides-Extra: sources.imap
Requires-Dist: IMAPClient; extra == 'sources.imap'
Provides-Extra: outputs.rss
Requires-Dist: feedgen; extra == 'outputs.rss'
Provides-Extra: outputs.xmpp
Requires-Dist: sleekxmpp; extra == 'outputs.xmpp'
Provides-Extra: sources.github
Requires-Dist: requests; extra == 'sources.github'
